svoi_framework/__init__.py
svoi_framework/config.py
svoi_framework/event_dispatcher.py
svoi_framework/outbox_event_publisher.py
svoi_framework/py.typed
svoi_framework/query_dispatcher.py
svoi_framework/application/__init__.py
svoi_framework/application/date_time_provider.py
svoi_framework/application/uuid_provider.py
svoi_framework/di/__init__.py
svoi_framework/di/asyncpg.py
svoi_framework/di/sql_alchemy.py
svoi_framework/domain/__init__.py
svoi_framework/domain/aggregate.py
svoi_framework/fastapi/__init__.py
svoi_framework/fastapi/instrument/__init__.py
svoi_framework/fastapi/instrument/jaeger.py
svoi_framework/fastapi/instrument/prometheus.py
svoi_framework/unit_of_work/__init__.py
svoi_framework/unit_of_work/data_mapper.py
svoi_framework/unit_of_work/repository.py
svoi_framework/unit_of_work/uow.py
svoi_framework/unit_of_work/sqlalchemy/__init__.py
svoi_framework/unit_of_work/sqlalchemy/repository.py
svoi_framework/unit_of_work/sqlalchemy/unit_of_work.py
svoi_framework-0.6.4.dist-info/METADATA
svoi_framework-0.6.4.dist-info/WHEEL
svoi_framework-0.6.4.dist-info/RECORD
