Metadata-Version: 2.4
Name: svoi_framework
Version: 0.6.4
Summary: Add your description here
Requires-Python: >=3.13
Requires-Dist: asyncpg>=0.30.0
Requires-Dist: dishka>=1.6.0
Requires-Dist: fastapi>=0.116.1
Requires-Dist: opentelemetry-api>=1.36.0
Requires-Dist: opentelemetry-exporter-otlp>=1.36.0
Requires-Dist: opentelemetry-instrumentation-fastapi>=0.57b0
Requires-Dist: opentelemetry-sdk>=1.36.0
Requires-Dist: prometheus-client>=0.22.1
Requires-Dist: prometheus-fastapi-instrumentator>=7.1.0
Requires-Dist: pydantic>=2.11.7
Requires-Dist: pyyaml>=6.0.2
Requires-Dist: sqlalchemy[asyncio]>=2.0.43
